osrs_prices/__init__.py
osrs_prices/client.py
osrs_prices/py.typed
osrs_prices-0.1.2.dist-info/METADATA
osrs_prices-0.1.2.dist-info/WHEEL
osrs_prices-0.1.2.dist-info/licenses/LICENSE
osrs_prices-0.1.2.dist-info/RECORD
