Metadata-Version: 2.3
Name: osrs-prices
Version: 0.1.2
Summary: A Python client for the RuneScape Wiki Prices API
Project-URL: Homepage, https://github.com/mattflow/osrs-prices
Project-URL: Repository, https://github.com/mattflow/osrs-prices
Project-URL: Documentation, https://github.com/mattflow/osrs-prices#readme
Author-email: Matt Flowers <mattmflowers28@gmail.com>
License: MIT
Keywords: grand exchange,osrs,prices,runescape
Classifier: Development Status :: 4 - Beta
Classifier: Intended Audience :: Developers
Classifier: License :: OSI Approved :: MIT License
Classifier: Programming Language :: Python :: 3
Classifier: Programming Language :: Python :: 3.9
Classifier: Programming Language :: Python :: 3.10
Classifier: Programming Language :: Python :: 3.11
Classifier: Programming Language :: Python :: 3.12
Requires-Python: >=3.9
Requires-Dist: httpx>=0.27.2
Requires-Dist: pandas-stubs>=2.2.2.240807
Requires-Dist: pandas>=2.2.3
Requires-Dist: pydantic>=2.10.2
